[{"line":1,"elements":[{"line":3,"name":"","description":"","type":"background","keyword":"Background","steps":[{"result":{"duration":1001000,"status":"passed"},"line":4,"name":"Encender el movil","match":{"location":"StepsMovil.encender_movil()"},"keyword":"Given "},{"result":{"duration":54917949800,"status":"passed"},"line":5,"name":"Abrir la aplicacion","match":{"location":"StepsMovil.abrir_aplicacion()"},"keyword":"And "},{"result":{"duration":1360904500,"status":"passed"},"line":6,"name":"Se visualiza la aplicacion","match":{"location":"StepsMovil.se_visualiza_aplicacion()"},"keyword":"And "}]},{"start_timestamp":"2022-07-29T11:49:17.230Z","line":10,"name":"Reportar un bug","description":"","id":"reportar-un-bug;reportar-un-bug","type":"scenario","keyword":"Scenario","steps":[{"result":{"duration":822382500,"status":"passed"},"line":11,"name":"Hacer clic en el menu","match":{"location":"StepsMovil.clic_en_menu()"},"keyword":"And "},{"result":{"duration":1450562400,"status":"passed"},"line":12,"name":"Hacer clic en la opcion Report a Bug","match":{"location":"StepsMovil.clic_en_report_bug()"},"keyword":"And "},{"result":{"duration":1699658500,"status":"passed"},"line":13,"name":"Escribir el bug","match":{"location":"StepsMovil.escribir_bug()"},"keyword":"And "},{"result":{"duration":936491300,"status":"passed"},"line":14,"name":"Hacer clic en enviar","match":{"location":"StepsMovil.clic_enviar()"},"keyword":"And "},{"result":{"duration":1641955400,"status":"passed"},"line":15,"name":"Comprobar que el mensaje se ha enviado","match":{"location":"StepsMovil.comprobar_mensaje_enviado()"},"keyword":"Then "}],"tags":[{"name":"@bug"}]}],"name":"Reportar un bug","description":"","id":"reportar-un-bug","keyword":"Feature","uri":"file:src/test/features/report_bug.feature","tags":[]}]